meix/__init__.py
meix/cli.py
meix/meix.py
meix-0.3.0.dist-info/METADATA
meix-0.3.0.dist-info/RECORD
meix-0.3.0.dist-info/WHEEL
meix-0.3.0.dist-info/entry_points.txt
meix-0.3.0.dist-info/top_level.txt
